demo_reader_cahvs/__init__.py
demo_reader_cahvs/__main__.py
demo_reader_cahvs/multireader.py
demo_reader_cahvs/compressed/__init__.py
demo_reader_cahvs/compressed/bzipped.py
demo_reader_cahvs/compressed/gzipped.py
demo_reader_cahvs/util/__init__.py
demo_reader_cahvs/util/writer.py
demo_reader_cahvstar-0.0.1.dist-info/METADATA
demo_reader_cahvstar-0.0.1.dist-info/WHEEL
demo_reader_cahvstar-0.0.1.dist-info/top_level.txt
demo_reader_cahvstar-0.0.1.dist-info/RECORD
