Metadata-Version: 2.1
Name: demo-reader-cahvstar
Version: 0.0.1
Summary: Tools for reading various file formats
Home-page: UNKNOWN
License: UNKNOWN
Platform: UNKNOWN
